GraphicsMilensAtual/__init__.py
GraphicsMilensAtual/graf.py
GraphicsMilensAtual-1.1.7.dist-info/LICENSE
GraphicsMilensAtual-1.1.7.dist-info/METADATA
GraphicsMilensAtual-1.1.7.dist-info/WHEEL
GraphicsMilensAtual-1.1.7.dist-info/top_level.txt
GraphicsMilensAtual-1.1.7.dist-info/RECORD
